{"chunk_id": "www.ft.com_companies_financial-services__chunk0", "source": "www.ft.com_companies_financial-services", "chunk_index": 0, "fetch_date": null, "generated_at": "2025-10-24T23:03:49.089494Z", "text": "<!-- source: www.ft.com_companies_financial-services  extracted: 2025-10-24T23:03:48.612357 UTC -->\n\nFinancial services\n\nFriday, 24 October, 2025 JPMorgan Chase & Co JPMorgan asks court to end legal fee payments for Charlie Javice Frank founder and another executive convicted of defrauding bank have had expenses covered under 2021 sale agreement 1 hour ago\n\nFrank founder and another executive convicted of defrauding bank have had expenses covered under 2021 sale agreement\n\nFriday, 24 October, 2025 NatWest Group NatWest profits hit highest since before 2008 bailout Investors buoyed by guidance upgrade and 30% rise in profits\n\nInvestors buoyed by guidance upgrade and 30% rise in profits\n\nFriday, 24 October, 2025 Private equity Why everyone is trying to sell you private assets right now Wealth managers are keen to promote semi-liquid funds to a new group of clients\n\nWealth managers are keen to promote semi-liquid funds to a new group of clients\n\nFriday, 24 October, 2025 Pensions industry Pension funds scoop up ex-private equity executives Prolonged downturn in dealmaking has meant fewer opportunities and squeeze on pay\n\nProlonged downturn in dealmaking has meant fewer opportunities and squeeze on pay\n\nFriday, 24 October, 2025 The Big Read Can Fidelity keep its grip on America’s investments? A vast distribution network helped the asset manager navigate the shift to passive investing, but new challenges are looming\n\nA vast distribution network helped the asset manager navigate the shift to passive investing, but new challenges are looming\n\nThursday, 23 October, 2025 Blackstone Group LP Blackstone says era of bumper private-credit returns has ended Comments by president Jonathan Gray come as private capital group reports better than expected results\n\nComments by president Jonathan Gray come as private capital group reports better than expected results\n\nThursday, 23 October, 2025 Venture capital investment Revolut and Spotify investor to stop raising outside funds Lakestar, one of Europe’s top tech venture firms run by Klaus Hommels, seeks to maximise existing deals\n\nLakestar, one of Europe’s top tech venture firms run by Klaus Hommels, seeks to maximise existing deals\n\nThursday, 23 October, 2025 Lloyds Banking Group Lloyds profits plunge 40% on car finance scandal UK high-street bank took £800mn charge linked to motor commissions, offsetting growth in net income\n\nUK high-street bank took £800mn charge linked to motor commissions, offsetting growth in net income\n\nThursday, 23 October, 2025 St James’s Place inflows surge ahead of fee changes Schroders reports new business boost, while AJ Bell boss warns of ‘damaging uncertainty’ before Budget\n\nSchroders reports new business boost, while AJ Bell boss warns of ‘damaging uncertainty’ before Budget\n\nThursday, 23 October, 2025 Money laundering Former Citi banker jailed over role in Singapore money-laundering scandal The case resulted in the city-state tightening regulations around family offices\n\nThe case res"}